.long-description.html
CHANGES.txt
MANIFEST.in
Makefile
README.rst
requirements.txt
setup.py
django_pci_auth/__init__.py
django_pci_auth/admin.py
django_pci_auth/forms.py
django_pci_auth/models.py
django_pci_auth/signals.py
django_pci_auth/tests.py
django_pci_auth/utils.py
django_pci_auth/validators.py
django_pci_auth/views.py
django_pci_auth.egg-info/PKG-INFO
django_pci_auth.egg-info/SOURCES.txt
django_pci_auth.egg-info/dependency_links.txt
django_pci_auth.egg-info/requires.txt
django_pci_auth.egg-info/top_level.txt
django_pci_auth/templates/account/locked_out_email.txt
django_pci_auth/templates/registration/password_change_form.html
docs/LICENSE.txt
docs/MODELS.rst
docs/NOTES.rst
docs/screenshot-ajax.png
docs/screenshot-axes.png
docs/screenshot-index.png
docs/screenshot-log.png