Metadata-Version: 1.0
Name: django-pci-auth
Version: 0.1.1
Summary: Provides change password validation with AJAX support and history check.
Home-page: https://github.com/django-pci/django-pci-auth
Author: Alex Clark
Author-email: aclark@aclark.net
License: UNKNOWN
Platform: UNKNOWN
